topsis_nihar_102303012/__init__.py
topsis_nihar_102303012/cli.py
topsis_nihar_102303012/topsis.py
topsis_nihar_102303012-1.0.0.dist-info/licenses/LICENSE
topsis_nihar_102303012-1.0.0.dist-info/METADATA
topsis_nihar_102303012-1.0.0.dist-info/WHEEL
topsis_nihar_102303012-1.0.0.dist-info/entry_points.txt
topsis_nihar_102303012-1.0.0.dist-info/top_level.txt
topsis_nihar_102303012-1.0.0.dist-info/RECORD
