Metadata-Version: 2.4
Name: Topsis-Nihar-102303012
Version: 1.0.0
Summary: TOPSIS implementation command line package
Author: Nihar Sharma
Author-email: nsharma3_be23@thapar.edu
Platform: any
Requires-Python: >=3.8
License-File: LICENSE
Requires-Dist: pandas
Requires-Dist: numpy
Dynamic: license-file
